{
  "sections": {
    "breadcrumbs": {
      "type": "breadcrumbs",
      "settings": {
        "hide_mobile": false
      }
    },
    "2a10c728-dc63-4972-83ab-ea7a4c57830d": {
      "type": "section-video-banner",
      "blocks": {
        "template--18576745595209__2a10c728-dc63-4972-83ab-ea7a4c57830d-title-1": {
          "type": "title",
          "settings": {
            "title": "Planterad & Klar ®",
            "title_size": "h2"
          }
        },
        "template--18576745595209__2a10c728-dc63-4972-83ab-ea7a4c57830d-text-1": {
          "type": "text",
          "settings": {
            "text": "<p>Har du inte tid, lust eller kunskap att plantera dina plantor? Lugn, våra experter hjälper dig att få det perfekta resultatet. Med denna produkt köper du en färdig häck, smart, lätt och prisvärt. När du köper en färdig häck planteras alla plantor av våra erfarna trädgårdsmästare på absolut bästa sätt.<\/p>"
          }
        },
        "template--18576745595209__2a10c728-dc63-4972-83ab-ea7a4c57830d-usp-1": {
          "type": "usp",
          "settings": {
            "usp": "<p><strong>36 månaders garanti<\/strong><\/p>"
          }
        },
        "template--18576745595209__2a10c728-dc63-4972-83ab-ea7a4c57830d-usp-2": {
          "type": "usp",
          "settings": {
            "usp": "<p><strong>Utförs av utbildade professionella medarbetare. <\/strong><\/p>"
          }
        },
        "template--18576745595209__2a10c728-dc63-4972-83ab-ea7a4c57830d-usp-3": {
          "type": "usp",
          "settings": {
            "usp": "<p><strong>Delbetala i 24 månader med Svea finnans.<\/strong><\/p>"
          }
        },
        "dea3dcf2-5cb8-4537-bd18-95f8c7896a1d": {
          "type": "usp",
          "settings": {
            "usp": "<p><strong>Tydliga skötselinstruktioner direkt på plats.<\/strong><\/p>"
          }
        },
        "66523628-c6e9-44a8-a7bc-eb055712d9af": {
          "type": "usp",
          "settings": {
            "usp": "<p><strong>Droppbevattning installeras alltid.<\/strong><\/p>"
          }
        },
        "a2bc6304-2f59-4b93-8e6d-b122f37f67a1": {
          "type": "usp",
          "settings": {
            "usp": "<p><strong>Vi använder enbart jordprodukter från Hasselfors.<\/strong><\/p>"
          }
        },
        "template--18576745595209__2a10c728-dc63-4972-83ab-ea7a4c57830d-buttons-1": {
          "type": "buttons",
          "disabled": true,
          "settings": {
            "link_text_1": "Button",
            "link_url_1": "\/",
            "button_color_palette_1": "accent",
            "link_text_2": "",
            "link_url_2": "",
            "button_color_palette_2": "light",
            "show_link": false
          }
        }
      },
      "block_order": [
        "template--18576745595209__2a10c728-dc63-4972-83ab-ea7a4c57830d-title-1",
        "template--18576745595209__2a10c728-dc63-4972-83ab-ea7a4c57830d-text-1",
        "template--18576745595209__2a10c728-dc63-4972-83ab-ea7a4c57830d-usp-1",
        "template--18576745595209__2a10c728-dc63-4972-83ab-ea7a4c57830d-usp-2",
        "template--18576745595209__2a10c728-dc63-4972-83ab-ea7a4c57830d-usp-3",
        "dea3dcf2-5cb8-4537-bd18-95f8c7896a1d",
        "66523628-c6e9-44a8-a7bc-eb055712d9af",
        "a2bc6304-2f59-4b93-8e6d-b122f37f67a1",
        "template--18576745595209__2a10c728-dc63-4972-83ab-ea7a4c57830d-buttons-1"
      ],
      "settings": {
        "overlay_opacity": 0,
        "color_palette": "white",
        "layout": "image-left",
        "text_position": "text-start",
        "video_url": "https:\/\/www.youtube.com\/watch?v=IJYERVOiUkA",
        "video_alt_text": "",
        "video": "shopify:\/\/files\/videos\/Plantering av färdiga häckelement i Göteborg 2023 (ingen grafik).mp4",
        "spacing_desktop": 0,
        "spacing_mobile": 0
      }
    },
    "ff20ecfb-7624-40d2-8a34-eaa3a487fb53": {
      "type": "section-promo-gallery",
      "blocks": {
        "template--16120548622499__ff20ecfb-7624-40d2-8a34-eaa3a487fb53-1669135682fedbe361-0": {
          "type": "image",
          "disabled": true,
          "settings": {
            "image": "shopify:\/\/shop_images\/Liuster_kampanj_2048x_27ff3d7c-3f1d-4bec-ac31-a8b820c26120_2048x-compressed.jpg",
            "overlay_opacity": 0,
            "color_palette": "white",
            "button_color_palette": "accent",
            "text_position": "text-center",
            "title_size": "h2",
            "title": "Thuja Brabant",
            "text": "<p>Denna växt passar dig som vill skapa insynskydd<\/p>",
            "link_text": "Thuja Brabant",
            "link_url": "\/",
            "show_link": false,
            "title_size_mobile": "mobile-size-18"
          }
        },
        "template--16120548622499__ff20ecfb-7624-40d2-8a34-eaa3a487fb53-1669135682fedbe361-1": {
          "type": "image",
          "settings": {
            "overlay_opacity": 0,
            "color_palette": "white",
            "button_color_palette": "accent",
            "text_position": "text-center",
            "title_size": "h2",
            "title": "Promo banner",
            "text": "<p>Describe a product or make an announcement<\/p>",
            "link_text": "Button",
            "link_url": "\/",
            "show_link": false,
            "title_size_mobile": "mobile-size-18"
          }
        },
        "template--16120548622499__ff20ecfb-7624-40d2-8a34-eaa3a487fb53-1669135682fedbe361-2": {
          "type": "image",
          "settings": {
            "overlay_opacity": 0,
            "color_palette": "white",
            "button_color_palette": "accent",
            "text_position": "text-center",
            "title_size": "h2",
            "title": "Promo banner",
            "text": "<p>Describe a product or make an announcement<\/p>",
            "link_text": "Button",
            "link_url": "\/",
            "show_link": false,
            "title_size_mobile": "mobile-size-18"
          }
        },
        "a189e1f9-c150-4411-a5b5-cd0cc85d242e": {
          "type": "image",
          "settings": {
            "overlay_opacity": 0,
            "color_palette": "white",
            "button_color_palette": "accent",
            "text_position": "text-center",
            "title_size": "h2",
            "title": "Promo banner",
            "text": "<p>Describe a product or make an announcement<\/p>",
            "link_text": "Button",
            "link_url": "\/",
            "show_link": false,
            "title_size_mobile": "mobile-size-18"
          }
        }
      },
      "block_order": [
        "template--16120548622499__ff20ecfb-7624-40d2-8a34-eaa3a487fb53-1669135682fedbe361-0",
        "template--16120548622499__ff20ecfb-7624-40d2-8a34-eaa3a487fb53-1669135682fedbe361-1",
        "template--16120548622499__ff20ecfb-7624-40d2-8a34-eaa3a487fb53-1669135682fedbe361-2",
        "a189e1f9-c150-4411-a5b5-cd0cc85d242e"
      ],
      "disabled": true,
      "settings": {
        "style": "style_one",
        "items_width": 4,
        "width": "boxed",
        "space_between": 16,
        "image_zoom": true,
        "layout_mobile": "rows",
        "spacing_desktop": 50,
        "spacing_mobile": 30
      }
    },
    "365cd7c7-375a-4824-bffe-1cb0b285a36a": {
      "type": "section-featured-collection",
      "disabled": true,
      "settings": {
        "collection": "thuja-brabant",
        "limit": 8,
        "number_of_items": 6,
        "text_alignment": "start",
        "title_size": "h3",
        "title": "Thuja Brabant",
        "text": "<p>Thuja <\/p>",
        "link_text": "Se alla",
        "button_color_palette": "dark",
        "show_link": true,
        "enable_quick_buy_desktop": true,
        "enable_quick_buy_mobile": true,
        "enable_quick_buy_drawer": false,
        "enable_quick_buy_qty_selector": true,
        "enable_quick_buy_compact": false,
        "spacing_desktop": 50,
        "spacing_mobile": 30
      }
    },
    "main-collection": {
      "type": "main-collection",
      "blocks": {
        "title": {
          "type": "title",
          "disabled": true,
          "settings": {
            "text_alignment": "left"
          }
        },
        "423fb7f6-2c97-4420-8211-d45378349d2a": {
          "type": "description",
          "disabled": true,
          "settings": {
            "text_alignment": "left",
            "enable_read_more": false
          }
        },
        "sorting": {
          "type": "sorting",
          "settings": {
          }
        },
        "product_grid": {
          "type": "product_grid",
          "settings": {
          }
        }
      },
      "block_order": [
        "title",
        "423fb7f6-2c97-4420-8211-d45378349d2a",
        "sorting",
        "product_grid"
      ],
      "settings": {
        "pagination_qty": 48,
        "pagination_type": "pages",
        "show_amount_of_products_in_collection": true,
        "productview_type": "grid",
        "products_per_row": 4,
        "show_collection_image": false,
        "enable_filters": false,
        "enable_menu": false,
        "filters_menu_alignment": "left",
        "filter_menu": "",
        "filter_sticky": true,
        "filters_show_more_limit": 10,
        "enable_quick_buy_desktop": true,
        "enable_quick_buy_mobile": true,
        "enable_quick_buy_drawer": false,
        "enable_quick_buy_qty_selector": true,
        "enable_quick_buy_compact": true,
        "products_per_row_mobile": "2",
        "filter_mobile_sticky": false
      }
    },
    "793cccbd-a07e-406e-ae9d-a2d10948897b": {
      "type": "image-gallery-custom",
      "blocks": {
        "29e73b3c-c021-4ec9-a6b8-fbf9c8fea097": {
          "type": "Image_banner",
          "settings": {
            "active__image": "active",
            "image": "shopify:\/\/shop_images\/Thuja_Brabant_200cm_1000x_1e57d520-b750-49e9-b2fd-e678ebf44d9c.webp",
            "heading": "",
            "text__alignment": "text__right",
            "description": "<h3>Malmö<\/h3><p><strong>Thuja Brabant 180-200cm<\/strong><\/p><p>2022-09-12<\/p>",
            "button_label": "",
            "button_url": ""
          }
        },
        "7ee07db1-057e-4b95-89c0-22787915c2d6": {
          "type": "Image_banner",
          "settings": {
            "active__image": "active",
            "image": "shopify:\/\/shop_images\/Thuja_Smaragd_110cm_4_600x_1000x_8fb95740-615f-4ccd-8543-b6b89787e614.webp",
            "heading": "",
            "text__alignment": "text__right",
            "description": "<h3>Göteborg<\/h3><p><strong>Thuja Smaragd 90cm<\/strong><\/p><p>2022-10-08<\/p>",
            "button_label": "",
            "button_url": ""
          }
        },
        "a75250c7-d4e6-4e1b-a0a9-5f70d4d34329": {
          "type": "Image_banner",
          "settings": {
            "active__image": "active",
            "image": "shopify:\/\/shop_images\/ezgif.com-webp-to-jpg_2_4219f0b0-e45b-4bda-afee-9a9823ebd22f.webp",
            "heading": "",
            "text__alignment": "text__right",
            "description": "<h3>Åkersberga<\/h3><p><strong>Thuja Smaragd 180-200cm<\/strong><\/p><p>2022-10-15<\/p>",
            "button_label": "",
            "button_url": ""
          }
        },
        "9f7eaf45-8df0-49d8-8717-99443305a463": {
          "type": "Image_banner",
          "settings": {
            "active__image": "active",
            "image": "shopify:\/\/shop_images\/Thuja_Smaragd_170cm_2_1000x_0846feb4-e506-4f67-87ad-98c3d3363293.webp",
            "heading": "",
            "text__alignment": "text__right",
            "description": "<h3>Stockholm<\/h3><p><strong>Thuja Smaragd 160-180cm<\/strong><\/p><p>2022-08-03<\/p>",
            "button_label": "",
            "button_url": ""
          }
        },
        "3e11ad35-a7a7-4d71-942b-a977088994f6": {
          "type": "Image_banner",
          "settings": {
            "active__image": "active",
            "image": "shopify:\/\/shop_images\/Thuja_Brabant_160_1000x_c4edb9c2-3571-4787-b344-660f533caeb4.webp",
            "heading": "",
            "text__alignment": "text__right",
            "description": "<h3>Linköping<\/h3><p><strong>Thuja Brabant 140-160cm<\/strong><\/p><p>2022-07-22<\/p>",
            "button_label": "",
            "button_url": ""
          }
        },
        "599fc891-f96a-42a4-878d-882cee3fbae1": {
          "type": "Image_banner",
          "settings": {
            "active__image": "active",
            "image": "shopify:\/\/shop_images\/ezgif.com-webp-to-jpg_3_d7f1000a-27f6-473c-bd76-44e3cec8c522.webp",
            "heading": "",
            "text__alignment": "text__right",
            "description": "<h3>Helsingborg<\/h3><p><strong>Lagerhägg Novita 100-120cm<\/strong><\/p><p>2022-09-20<\/p>",
            "button_label": "",
            "button_url": ""
          }
        }
      },
      "block_order": [
        "29e73b3c-c021-4ec9-a6b8-fbf9c8fea097",
        "7ee07db1-057e-4b95-89c0-22787915c2d6",
        "a75250c7-d4e6-4e1b-a0a9-5f70d4d34329",
        "9f7eaf45-8df0-49d8-8717-99443305a463",
        "3e11ad35-a7a7-4d71-942b-a977088994f6",
        "599fc891-f96a-42a4-878d-882cee3fbae1"
      ],
      "settings": {
        "color_palette": "light",
        "overlay_opacity": 1,
        "show_card": 3,
        "row-gap": 10,
        "col-gap": 10,
        "space-top": 10,
        "space-bottom": 10
      }
    },
    "4ce362b3-c2eb-4ce1-9d83-08190ddc7820": {
      "type": "section-contact-form",
      "blocks": {
        "template--16120548622499__4ce362b3-c2eb-4ce1-9d83-08190ddc7820-166914131982366b05-0": {
          "type": "text",
          "settings": {
            "title": "Namn",
            "placeholder": "Namn",
            "required": true
          }
        },
        "template--16120548622499__4ce362b3-c2eb-4ce1-9d83-08190ddc7820-166914131982366b05-1": {
          "type": "text",
          "settings": {
            "title": "Företagsnamn",
            "placeholder": "Företagsnamn",
            "required": false
          }
        },
        "template--16120548622499__4ce362b3-c2eb-4ce1-9d83-08190ddc7820-166914131982366b05-2": {
          "type": "email",
          "settings": {
            "title": "E-post",
            "placeholder": "E-post"
          }
        },
        "template--16120548622499__4ce362b3-c2eb-4ce1-9d83-08190ddc7820-166914131982366b05-3": {
          "type": "tel",
          "settings": {
            "title": "Telefonnummer",
            "placeholder": "Telefonnummer",
            "required": false
          }
        },
        "template--16120548622499__4ce362b3-c2eb-4ce1-9d83-08190ddc7820-166914131982366b05-4": {
          "type": "text",
          "settings": {
            "title": "Ämne",
            "placeholder": "Ämne",
            "required": false
          }
        },
        "template--16120548622499__4ce362b3-c2eb-4ce1-9d83-08190ddc7820-166914131982366b05-5": {
          "type": "textarea",
          "settings": {
            "title": "Meddelande",
            "placeholder": "Meddelande",
            "required": true
          }
        }
      },
      "block_order": [
        "template--16120548622499__4ce362b3-c2eb-4ce1-9d83-08190ddc7820-166914131982366b05-0",
        "template--16120548622499__4ce362b3-c2eb-4ce1-9d83-08190ddc7820-166914131982366b05-1",
        "template--16120548622499__4ce362b3-c2eb-4ce1-9d83-08190ddc7820-166914131982366b05-2",
        "template--16120548622499__4ce362b3-c2eb-4ce1-9d83-08190ddc7820-166914131982366b05-3",
        "template--16120548622499__4ce362b3-c2eb-4ce1-9d83-08190ddc7820-166914131982366b05-4",
        "template--16120548622499__4ce362b3-c2eb-4ce1-9d83-08190ddc7820-166914131982366b05-5"
      ],
      "settings": {
        "alignment": "start",
        "title_size": "h3",
        "title": "Har du frågor om Planterad & Klar®?",
        "button_color_palette": "dark",
        "show_placeholder": true,
        "compact": false,
        "spacing_desktop": 50,
        "spacing_mobile": 30
      }
    }
  },
  "order": [
    "breadcrumbs",
    "2a10c728-dc63-4972-83ab-ea7a4c57830d",
    "ff20ecfb-7624-40d2-8a34-eaa3a487fb53",
    "365cd7c7-375a-4824-bffe-1cb0b285a36a",
    "main-collection",
    "793cccbd-a07e-406e-ae9d-a2d10948897b",
    "4ce362b3-c2eb-4ce1-9d83-08190ddc7820"
  ]
}